.gitignore
LICENSE
README.md
setup.py
dayfilter/__init__.py
dayfilter/core.py
dayfilter/logic.py
dayfilter/post_process.py
dayfilter/version.py
dayfilter.egg-info/PKG-INFO
dayfilter.egg-info/SOURCES.txt
dayfilter.egg-info/dependency_links.txt
dayfilter.egg-info/requires.txt
dayfilter.egg-info/top_level.txt
tests/test1.py