Metadata-Version: 2.1
Name: dayfilter
Version: 0.2.1
Summary: Filter time-series based on sun movement
Home-page: https://github.com/yasirroni/dayfilter
Author: Muhammad Yasirroni
Author-email: muhammadyasirroni@gmail.com
License: UNKNOWN
Platform: UNKNOWN
Classifier: Programming Language :: Python
Classifier: Topic :: Scientific/Engineering
Classifier: License :: OSI Approved :: MIT License
Requires-Python: >3.6
License-File: LICENSE
